notix/__init__.py
notix/message.py
notix-0.0.1.dist-info/METADATA
notix-0.0.1.dist-info/WHEEL
notix-0.0.1.dist-info/top_level.txt
notix-0.0.1.dist-info/RECORD
