Metadata-Version: 2.1
Name: notix
Version: 0.0.1
Summary: A simple library for showing notifications.
Home-page: https://github.com/Pop1avok/notix/
Author: Pop1avok
Author-email: pop1avplov@example.com
Classifier: Programming Language :: Python :: 3
Classifier: License :: OSI Approved :: MIT License
Classifier: Operating System :: OS Independent
Requires-Python: >=3.6
